mlops_models/__init__.py
mlops_models/constant.py
mlops_models/sentiment.py
mlops_models/resources/models/sentiment-negative-en.txt
mlops_models/resources/models/sentiment-positive-en.txt
mlops_models-1.0.5.dist-info/METADATA
mlops_models-1.0.5.dist-info/WHEEL
mlops_models-1.0.5.dist-info/top_level.txt
mlops_models-1.0.5.dist-info/RECORD
