Metadata-Version: 2.1
Name: mlops-models
Version: 1.0.5
Summary: Service for ...
Home-page: https://github.com/FRI-Machine-Learning-Operations-22-23/mlops-01-hands-on
Author: Bostjan Kaluza
License: MIT License
Platform: UNKNOWN
Classifier: Environment :: Web Environment
Classifier: Intended Audience :: Developers
Classifier: License :: OSI Approved :: MIT License
Classifier: Operating System :: OS Independent
Classifier: Programming Language :: Python
Classifier: Programming Language :: Python :: 3.7
